x_auth/controller.py
x_auth/enums.py
x_auth/exceptions.py
x_auth/middleware.py
x_auth/models.py
x_auth/types.py
xn_auth-0.2.54.dist-info/METADATA
xn_auth-0.2.54.dist-info/WHEEL
xn_auth-0.2.54.dist-info/top_level.txt
xn_auth-0.2.54.dist-info/RECORD
